<?xml version="1.0" encoding="utf-8"?>
<Defs>
    <!-- ========================= Work tables ==========================-->
    <ThingDef ParentName="BenchBase">
        <defName>MRC_EssenceRefinery</defName>
        <label>essence refinery</label>
        <thingClass>Building_WorkTable</thingClass>
        <description>A place where skilled farmers and crafters can produce resources from plant essences.</description>
        <graphicData>
            <texPath>Buildings/Production/EssenceRefinery</texPath>
            <graphicClass>Graphic_Multi</graphicClass>
            <shaderType>CutoutComplex</shaderType>
            <drawSize>(3.5,1.5)</drawSize>
        </graphicData>
        <costStuffCount>75</costStuffCount>
        <costList>
            <ComponentIndustrial>4</ComponentIndustrial>
        </costList>
        <stuffCategories>
            <li>Metallic</li>
            <li>Woody</li>
            <li>Stony</li>
        </stuffCategories>
        <fillPercent>0.5</fillPercent>
        <useHitPoints>True</useHitPoints>
        <statBases>
            <WorkToBuild>2000</WorkToBuild>
            <MaxHitPoints>180</MaxHitPoints>
            <Flammability>1.0</Flammability>
        </statBases>
        <size>(3,1)</size>
        <designationCategory>Production</designationCategory>
        <passability>PassThroughOnly</passability>
        <pathCost>60</pathCost>
        <hasInteractionCell>True</hasInteractionCell>
        <interactionCellOffset>(0,0,-1)</interactionCellOffset>
        <surfaceType>Item</surfaceType>
        <tickerType>Normal</tickerType>
        <constructionSkillPrerequisite>4</constructionSkillPrerequisite>
        <inspectorTabs>
            <li>ITab_Bills</li>
        </inspectorTabs>
        <building>
          <spawnedConceptLearnOpportunity>BillsTab</spawnedConceptLearnOpportunity>
        </building>
        <comps>
            <li Class="CompProperties_AffectedByFacilities">
                <linkableFacilities>
                    <li>MRC_MysticalAnalyzer</li>
                    <li>ToolCabinet</li>
                </linkableFacilities>
            </li>
        </comps>
        <placeWorkers>
            <li>PlaceWorker_ShowFacilitiesConnections</li>
            <li>PlaceWorker_PreventInteractionSpotOverlap</li>
        </placeWorkers>
        <researchPrerequisites>
            <li>MRC_EssenceRefining</li>
        </researchPrerequisites>
    </ThingDef>
</Defs>